kpfpwd.py
kpfpwd-0.0.2.1.dist-info/LICENSE
kpfpwd-0.0.2.1.dist-info/METADATA
kpfpwd-0.0.2.1.dist-info/WHEEL
kpfpwd-0.0.2.1.dist-info/entry_points.txt
kpfpwd-0.0.2.1.dist-info/top_level.txt
kpfpwd-0.0.2.1.dist-info/RECORD
