Metadata-Version: 2.1
Name: kpfpwd
Version: 0.0.2.1
Summary: KeePass password fetcher.
Author-email: أحمد المحمودي <aelmahmoudy@users.sourceforge.net>
License: GPL-3.0
Project-URL: homepage, https://gitlab.com/aelmahmoudy/kpfpwd
Project-URL: issues, https://gitlab.com/aelmahmoudy/kpfpwd/-/issues
Keywords: keepass,vault,cli
Classifier: Development Status :: 5 - Production/Stable
Classifier: Environment :: Console
Classifier: License :: OSI Approved :: GNU General Public License v3 (GPLv3)
Classifier: Operating System :: POSIX
Classifier: Programming Language :: Python :: 3
Classifier: Programming Language :: Python :: 3.8
Classifier: Programming Language :: Python :: 3.9
Classifier: Programming Language :: Python :: 3.10
Classifier: Programming Language :: Python :: 3.11
Classifier: Programming Language :: Python :: 3.12
Classifier: Programming Language :: Python :: Implementation :: PyPy
Requires-Python: >=3.7
License-File: LICENSE
Requires-Dist: pyotp>=2.9.0
Requires-Dist: pykeepass
Requires-Dist: setuptools; python_version < "3.8"
